ffwrapy/__init__.py
ffwrapy/ffmedia.py
ffwrapy-1.1.0.dist-info/licenses/LICENSE
ffwrapy-1.1.0.dist-info/METADATA
ffwrapy-1.1.0.dist-info/WHEEL
ffwrapy-1.1.0.dist-info/top_level.txt
ffwrapy-1.1.0.dist-info/RECORD
