Metadata-Version: 2.4
Name: ffwrapy
Version: 1.1.0
Summary: A fast, flexible Python wrapper for FFmpeg, FFprobe, and FFplay — fetch metadata, encode, split, play and run custom commands easily with real-time progress tracking.
Author: भाग्य ज्योति (Bhagya Jyoti)
License: Apache License Version 2.0
Project-URL: Homepage, https://github.com/BhagyaJyoti22006/ffwrapy
Project-URL: Repository, https://github.com/BhagyaJyoti22006/ffwrapy
Project-URL: Issues, https://github.com/BhagyaJyoti22006/ffwrapy/issues
Keywords: ffmpeg,ffprobe,ffplay,media,encoding,mux,remux,wrapper,python,video,audio,subtitle,vid,aud,sub,fetch,encode,split,play,thumbnail,transcode
Classifier: Programming Language :: Python :: 3
Classifier: License :: OSI Approved :: Apache Software License
Classifier: Operating System :: OS Independent
Classifier: Topic :: Multimedia :: Video
Classifier: Topic :: Multimedia :: Sound/Audio
Classifier: Development Status :: 5 - Production/Stable
Requires-Python: >=3.7
License-File: LICENSE
Dynamic: license-file
